hoja/__init__.py
hoja-0.1.0.dist-info/METADATA
hoja-0.1.0.dist-info/WHEEL
hoja-0.1.0.dist-info/RECORD
